[
	{
		"name":"木头",
		"level":1,
		"quality":1,
		"price":0,
		"combine":0
	},
	{
		"name":"小树枝",
		"level":1,
		"quality":2,
		"price":0,
		"combine":0
	},
	{
		"name":"硬木藤蔓",
		"level":1,
		"quality":3,
		"price":0,
		"combine":0
	},
	{
		"name":"石头",
		"level":1,
		"quality":1,
		"price":0,
		"combine":0
	},
	{
		"name":"铁矿",
		"level":1,
		"quality":2,
		"price":65,
		"combine":0
	},
	{
		"name":"燧石",
		"level":1,
		"quality":3,
		"price":0,
		"combine":0
	},
	{
		"name":"麻",
		"level":1,
		"quality":1,
		"price":0,
		"combine":0
	},
	{
		"name":"植物根茎",
		"level":1,
		"quality":2,
		"price":0,
		"combine":0
	},
	{
		"name":"骨头",
		"level":1,
		"quality":2,
		"price":0,
		"combine":0
	},
	{
		"name":"兽皮",
		"level":1,
		"quality":3,
		"price":0,
		"combine":0
	},

	{
		"name":"树脂",
		"level":2,
		"quality":2,
		"price":0,
		"combine":0
	},
	{
		"name":"木心",
		"level":2,
		"quality":3,
		"price":148,
		"combine":0
	},
	{
		"name":"小枝芽",
		"level":2,
		"quality":3,
		"price":0,
		"combine":0
	},
	{
		"name":"锡矿",
		"level":2,
		"quality":2,
		"price":73,
		"combine":0
	},
	{
		"name":"硫磺",
		"level":2,
		"quality":3,
		"price":0,
		"combine":0
	},
	{
		"name":"硝石",
		"level":2,
		"quality":3,
		"price":0,
		"combine":0
	},
	{
		"name":"麻茎杆",
		"level":2,
		"quality":2,
		"price":0,
		"combine":0
	},
	{
		"name":"麻茎皮",
		"level":2,
		"quality":3,
		"price":0,
		"combine":0
	},
	{
		"name":"麻籽",
		"level":2,
		"quality":3,
		"price":0,
		"combine":0
	},
	{
		"name":"爪子",
		"level":2,
		"quality":2,
		"price":0,
		"combine":0
	},
	{
		"name":"兽筋",
		"level":2,
		"quality":3,
		"price":0,
		"combine":0
	},

	{
		"name":"老柏木",
		"level":3,
		"quality":2,
		"price":54,
		"combine":0
	},
	{
		"name":"树油",
		"level":3,
		"quality":2,
		"price":86,
		"combine":0
	},
	{
		"name":"柏树叶",
		"level":3,
		"quality":3,
		"price":78,
		"combine":0
	},
	{
		"name":"铝矿",
		"level":3,
		"quality":2,
		"price":61,
		"combine":0
	},
	{
		"name":"蓝晶石",
		"level":3,
		"quality":3,
		"price":100,
		"combine":0
	},
	{
		"name":"亚麻叶",
		"level":3,
		"quality":2,
		"price":70,
		"combine":0
	},
	{
		"name":"亚麻花瓣",
		"level":3,
		"quality":3,
		"price":160,
		"combine":0
	},
	{
		"name":"油脂",
		"level":3,
		"quality":2,
		"price":63,
		"combine":0
	},
	{
		"name":"兽角",
		"level":3,
		"quality":3,
		"price":140,
		"combine":0
	},
	{
		"name":"高分子涂层",
		"level":3,
		"quality":3,
		"price":3000,
		"combine":0
	},
	{
		"name":"薄膜面料",
		"level":3,
		"quality":3,
		"price":2000,
		"combine":0
	},
	{
		"name":"麻绳",
		"level":3,
		"quality":3,
		"price":0,
		"combine":0
	},
	{
		"name":"胶水",
		"level":3,
		"quality":3,
		"price":0,
		"combine":0
	},
	{
		"name":"钉子",
		"level":3,
		"quality":3,
		"price":0,
		"combine":0
	},




	{
		"name":"粗布条",
		"level":1,
		"quality":2,
		"price":0,
		"combine":1,
		"combine_list":
		{
			"麻":15,
			"植物根茎":2
		}
	},
	{
		"name":"布",
		"level":2,
		"quality":3,
		"price":0,
		"combine":1,
		"combine_list":
		{
			"粗布条":1,
			"麻茎皮":1
		}
	},
	{
		"name":"塑料",
		"level":2,
		"quality":3,
		"price":0,
		"combine":1,
		"combine_list":
		{
			"树脂":8,
			"硝石":2,
			"布":1,
			"麻茎杆":2
		}
	},

	{
		"name":"生铁",
		"level":1,
		"quality":2,
		"price":0,
		"combine":1,
		"combine_list":
		{
			"铁矿":2,
			"小树枝":4
		}
	},
	{
		"name":"六角钉",
		"level":2,
		"quality":3,
		"price":0,
		"combine":1,
		"combine_list":
		{
			"生铁":2,
			"硬木藤蔓":4,
			"骨头":2
		}
	},
	{
		"name":"铁铸件",
		"level":2,
		"quality":3,
		"price":1000,
		"combine":0,
		"combine_list":
		{
			"锡矿":4,
			"铁矿":4,
			"木心":4
		}
	},
	{
		"name":"螺钉",
		"level":2,
		"quality":3,
		"price":0,
		"combine":1,
		"combine_list":
		{
			"铁铸件":1,
			"小枝芽":4,
			"麻籽":1,
			"硫磺":2
		}
	},
	{
		"name":"硬铝合金",
		"level":3,
		"quality":3,
		"price":0,
		"combine":1,
		"combine_list":
		{
			"铝矿":5,
			"锡矿":5,
			"老柏木":9,
			"树油":5
		}
	},
	{
		"name":"尼龙布",
		"level":3,
		"quality":3,
		"price":0,
		"combine":1,
		"combine_list":
		{
			"亚麻叶":3,
			"亚麻花瓣":1,
			"柏树叶":5
		}
	},
	{
		"name":"黑火药",
		"level":3,
		"quality":3,
		"price":0,
		"combine":1,
		"combine_list":
		{
			"木头":600,
			"石头":150,
			"燧石":2
		}
	},
	{
		"name":"无烟火药",
		"level":3,
		"quality":3,
		"price":0,
		"combine":1,
		"combine_list":
		{
			"黑火药":3,
			"硝石":1,
			"蓝晶石":5
		}
	},
	{
		"name":"木板",
		"level":3,
		"quality":3,
		"price":0,
		"combine":0,
		"combine_list":
		{
			"木头":120,
			"小树枝":2
		}
	},



	{
		"name":"普通弹药箱",
		"level":2,
		"quality":3,
		"price":0,
		"combine":1,
		"combine_list":
		{
			"无烟火药":2,
			"硬铝合金":2,
			"兽角":3,
			"木板":15
		}
	},
	{
		"name":"uzi",
		"level":2,
		"quality":3,
		"price":0,
		"combine":1,
		"combine_list":
		{
			"铁铸件":10,
			"六角钉":10,
			"爪子":20
		}
	},
	{
		"name":"复合弓",
		"level":2,
		"quality":3,
		"price":0,
		"combine":1,
		"combine_list":
		{
			"铁铸件":10,
			"螺钉":10,
			"兽筋":10,
			"胶水":8
		}
	},
	{
		"name":"警用卫衣",
		"level":2,
		"quality":3,
		"price":0,
		"combine":1,
		"combine_list":
		{
			"布":10,
			"塑料":10,
			"螺钉":10
		}
	},
	{
		"name":"防弹武装",
		"level":3,
		"quality":3,
		"price":0,
		"combine":1,
		"combine_list":
		{
			"尼龙布":10,
			"硬铝合金":10,
			"麻绳":10,
			"薄膜面料":4
		}
	},
	{
		"name":"战斗先锋",
		"level":3,
		"quality":3,
		"price":0,
		"combine":1,
		"combine_list":
		{
			"尼龙布":10,
			"铁铸件":12,
			"布":12,
			"薄膜面料":4
		}
	},
	{
		"name":"御寒棉帽",
		"level":3,
		"quality":3,
		"price":0,
		"combine":1,
		"combine_list":
		{
			"尼龙布":10,
			"兽筋":13,
			"布":12,
			"薄膜面料":4
		}
	},
	{
		"name":"ump9",
		"level":3,
		"quality":3,
		"price":0,
		"combine":1,
		"combine_list":
		{
			"硬铝合金":10,
			"六角钉":12,
			"油脂":24,
			"高分子涂层":4
		}
	},
	{
		"name":"汤姆逊",
		"level":3,
		"quality":3,
		"price":0,
		"combine":1,
		"combine_list":
		{
			"硬铝合金":10,
			"铁铸件":12,
			"钉子":10,
			"高分子涂层":4
		}
	},




	{
		"name":"test",
		"level":0,
		"quality":0,
		"price":0,
		"combine":0
	}


]